Workbook

Sheet Assumptions
A1: Wildgrove v0.7 — Economy Seed Model (ECO-1)
A2: Legend: BLUE cells = edit me (inputs/levers) · black = formulas · yellow fill = key tunables the doc references. All numbers are placeholders to be moved in balancing.
A4: Gathering
A5: g0 — base gather per agent per hour (tool tier 0) | B5: 120 | C5: Goods/hr. Doc §9: tuned UP from flock-era rates for a small crew.
A6: Active uplift (Tending bursts, avg while playing) | B6: 1.2 | C6: Multiplier on active hours only.
A7: Renown & prestige
A8: Renown factor — Renown per good handled | B8: 1.2 | C8: Warden craft XP + familiar XP per good, blended. Renown/hr = yield/hr x this.
A9: Offering credit total, run 1 (trade value) | B9: 4000 | C9: Sum of chosen verse slots across 4 verses; authored in rites.json later. Credited at fold row.
A10: Verdure target at first fold | B10: 10 | C10: Doc pacing target: ~10 Verdure, Day 1-2.
A11: Familiar XP per hour at post (postMatch=1) | B11: 250 | C11: famXP/sec x 3600, level-agnostic average.
A12: Kinship target for Gatherer 1 at first fold | B12: 2 | C12: First fold should visibly bank Kinship without trivialising it.
A13: Sinks
A14: Sink share — income available to discretionary sinks | B14: 0.5 | C14: Rest feeds offerings, kit, and consumption. Hour-six proof uses this.
A15: Replant base cost (node's own resource) | B15: 25 | C15: replantCost = base x r^L
A16: Replant ratio r | B16: 1.35
A17: Building bundle base (goods value) | B17: 250 | C17: buildingCost(L) = base x 1.25^L, paid in materials.
A18: Building ratio | B18: 1.25
A19: Provisions — Zone 2 bundle value | B19: 80 | C19: Trail Map bundles, authored per zone.
A20: Provisions — Zone 3 bundle value | B20: 300
A21: Provisions — Zone 4 bundle value | B21: 900
A22: Tool batch value — copper | B22: 60 | C22: Ingot batch trade value (5 ingots).
A23: Tool batch value — bronze | B23: 140
A24: Tool batch value — iron | B24: 320
A25: Planter — frame / bed / trellis values | B25: 120 | C25: Frame. Bed=180, trellis=260 on SinkLadder.
A26: Meaningful-purchase band — low (minutes) | B26: 10 | C26: Cheaper than this = trivial; not by itself 'meaningful'.
A27: Meaningful-purchase band — high (minutes) | B27: 90 | C27: Dearer than this with nothing else in band = a wall.
A28: Offline & the trail post (SP-1: balanced for eventual 2 posts; wanderers cover an unheld trail at x0.5)
A29: Evening tool multiplier (end of Day 1) | B29: 4 | C29: Flint+copper by bedtime.
A30: Evening richness multiplier | B30: 1.3
A31: Trail post factor — share of 4 ground-gatherers' demand one post hauls | B31: 0.75 | C31: DECIDED stance: one held post slightly under-hauls a full ground crew at like tier; Spare Wing (2nd post) relieves it. Hauling equipment assumes 2 posts eventually exist. Unheld trail: wanderers move x0.5 of one post.
A32: Offline cap — base / Store L1 / Store L2 (hours) | B32: 4 | C32: 6 and 8 used on Offline sheet.

Sheet Run Timeline
A1: Run 1 timeline — 8 active-hour blocks across Day 1–2 (overnight between H3 and H4)
A3: Hour | B3: Agents | C3: Tool mult | D3: Richness lvl | E3: Richness mult | F3: Planter mult | G3: Yield / hr | H3: Cum goods | I3: Renown / hr | J3: Cum Renown | K3: Notes
A4: H1 (Day 1) | B4: 2 | C4: 2 | D4: 1 | E4: =1+0.1*D4 -> 1.1 | F4: 1 | G4: =B4*Assumptions!$B$5*C4*E4*F4*Assumptions!$B$6 -> 633.6 | H4: =G4 -> 633.6 | I4: =G4*Assumptions!$B$8 -> 760.32 | J4: =I4 -> 760.32 | K4: Warden+G1; flint at ~4 min; Zone 2 map end of hour
A5: H2 | B5: 3 | C5: 3 | D5: 2 | E5: =1+0.1*D5 -> 1.2 | F5: 1 | G5: =B5*Assumptions!$B$5*C5*E5*F5*Assumptions!$B$6 -> 1555.2 | H5: =H4+G5 -> 2188.8 | I5: =G5*Assumptions!$B$8 -> 1866.24 | J5: =J4+I5 -> 2626.56 | K5: Verse 1 done ~30 min in -> gift event -> G2; copper mid-hour; Zone 3 map
A6: H3 | B6: 3 | C6: 4 | D6: 3 | E6: =1+0.1*D6 -> 1.3 | F6: 1.1 | G6: =B6*Assumptions!$B$5*C6*E6*F6*Assumptions!$B$6 -> 2471.04 | H6: =H5+G6 -> 4659.84 | I6: =G6*Assumptions!$B$8 -> 2965.248 | J6: =J5+I6 -> 5591.808 | K6: First planters; end of Day 1 session
A7: H4 (Day 2) | B7: 3 | C7: 4 | D7: 4 | E7: =1+0.1*D7 -> 1.4 | F7: 1.15 | G7: =B7*Assumptions!$B$5*C7*E7*F7*Assumptions!$B$6 -> 2782.08 | H7: =H6+G7 -> 7441.92 | I7: =G7*Assumptions!$B$8 -> 3338.496 | J7: =J6+I7 -> 8930.304 | K7: Post-overnight (see Offline sheet)
A8: H5 | B8: 3 | C8: 6 | D8: 5 | E8: =1+0.1*D8 -> 1.5 | F8: 1.2 | G8: =B8*Assumptions!$B$5*C8*E8*F8*Assumptions!$B$6 -> 4665.6 | H8: =H7+G8 -> 12107.52 | I8: =G8*Assumptions!$B$8 -> 5598.72 | J8: =J7+I8 -> 14529.024 | K8: Bronze lands; Zone 4 map
A9: H6 | B9: 3 | C9: 6 | D9: 6 | E9: =1+0.1*D9 -> 1.6 | F9: 1.25 | G9: =B9*Assumptions!$B$5*C9*E9*F9*Assumptions!$B$6 -> 5184 | H9: =H8+G9 -> 17291.52 | I9: =G9*Assumptions!$B$8 -> 6220.8 | J9: =J8+I9 -> 20749.824 | K9: THE HOUR-SIX PROOF ROW (SinkLadder)
A10: H7 | B10: 3 | C10: 8 | D10: 6 | E10: =1+0.1*D10 -> 1.6 | F10: 1.3 | G10: =B10*Assumptions!$B$5*C10*E10*F10*Assumptions!$B$6 -> 7188.48 | H10: =H9+G10 -> 24480 | I10: =G10*Assumptions!$B$8 -> 8626.176 | J10: =J9+I10 -> 29376 | K10: Iron on some crafts
A11: H8 (fold) | B11: 3 | C11: 8 | D11: 7 | E11: =1+0.1*D11 -> 1.7 | F11: 1.3 | G11: =B11*Assumptions!$B$5*C11*E11*F11*Assumptions!$B$6 -> 7637.76 | H11: =H10+G11 -> 32117.76 | I11: =G11*Assumptions!$B$8 -> 9165.312 | J11: =J10+I11+Assumptions!$B$9 -> 42541.312 | K11: Rite completes; offering credit lands; Migration
A13: Prestige solve (formulas — these SET the doc's constants)
A14: Lifetime Renown at fold | B14: =J11 -> 42541.312
A15: K (Verdure) to hit target at fold | B15: =B14/Assumptions!$B$10^2 -> 425.41312 | C15: verdureGain = FLOOR(SQRT(Renown/K)) -> K = Renown/target^2
A16: G1 run familiar XP (stationed all 8 h + capped offline ~6 h at 40%) | B16: =Assumptions!$B$11*8+Assumptions!$B$11*6*0.4 -> 2600
A17: K_f (Kinship) to hit target for G1 | B17: =B16/Assumptions!$B$12^2 -> 650
A18: Check: Verdure at fold with solved K | B18: =FLOOR(SQRT(B14/B15),1) -> 10
A19: Check: G1 Kinship at fold with solved K_f | B19: =FLOOR(SQRT(B16/B17),1) -> 2

Sheet SinkLadder
A1: Hour-six proof — is there always a meaningful next purchase? (band = 10–90 min of discretionary income)
A3: Hour | B3: Income/hr | C3: Discr./hr | D3: Replant next | E3: Building next | F3: Tool batch | G3: Provisions | H3: Planter next | I3: -> min | J3: -> min | K3: -> min | L3: -> min | M3: -> min | N3: Verdict
A4: H1 (Day 1) | B4: ='Run Timeline'!G4 -> 633.6 | C4: =B4*Assumptions!$B$14 -> 316.8 | D4: =Assumptions!$B$15*Assumptions!$B$16^'Run Timeline'!D4 -> 33.75 | E4: =Assumptions!$B$17*Assumptions!$B$18^1 -> 312.5 | F4: 100000 | G4: =Assumptions!$B$19 -> 80 | H4: 100000 | I4: =D4/C4*60 -> 6.3920455 | J4: =E4/C4*60 -> 59.185606 | K4: =F4/C4*60 -> 18939.394 | L4: =G4/C4*60 -> 15.151515 | M4: =H4/C4*60 -> 18939.394 | N4: =IF(SUMPRODUCT((I4:M4>=Assumptions!$B$26)*(I4:M4<=Assumptions!$B$27))>0,"OK",IF(SUMPRODUCT((I4:M4<Assumptions!$B$26))>0,"TRIVIAL-ONLY","WALL")) -> OK
A5: H2 | B5: ='Run Timeline'!G5 -> 1555.2 | C5: =B5*Assumptions!$B$14 -> 777.6 | D5: =Assumptions!$B$15*Assumptions!$B$16^'Run Timeline'!D5 -> 45.5625 | E5: =Assumptions!$B$17*Assumptions!$B$18^2 -> 390.625 | F5: =Assumptions!$B$22 -> 60 | G5: =Assumptions!$B$20 -> 300 | H5: 100000 | I5: =D5/C5*60 -> 3.515625 | J5: =E5/C5*60 -> 30.140818 | K5: =F5/C5*60 -> 4.6296296 | L5: =G5/C5*60 -> 23.148148 | M5: =H5/C5*60 -> 7716.0494 | N5: =IF(SUMPRODUCT((I5:M5>=Assumptions!$B$26)*(I5:M5<=Assumptions!$B$27))>0,"OK",IF(SUMPRODUCT((I5:M5<Assumptions!$B$26))>0,"TRIVIAL-ONLY","WALL")) -> OK
A6: H3 | B6: ='Run Timeline'!G6 -> 2471.04 | C6: =B6*Assumptions!$B$14 -> 1235.52 | D6: =Assumptions!$B$15*Assumptions!$B$16^'Run Timeline'!D6 -> 61.509375 | E6: =Assumptions!$B$17*Assumptions!$B$18^3 -> 488.28125 | F6: 100000 | G6: 100000 | H6: 120 | I6: =D6/C6*60 -> 2.987052 | J6: =E6/C6*60 -> 23.712182 | K6: =F6/C6*60 -> 4856.2549 | L6: =G6/C6*60 -> 4856.2549 | M6: =H6/C6*60 -> 5.8275058 | N6: =IF(SUMPRODUCT((I6:M6>=Assumptions!$B$26)*(I6:M6<=Assumptions!$B$27))>0,"OK",IF(SUMPRODUCT((I6:M6<Assumptions!$B$26))>0,"TRIVIAL-ONLY","WALL")) -> OK
A7: H4 (Day 2) | B7: ='Run Timeline'!G7 -> 2782.08 | C7: =B7*Assumptions!$B$14 -> 1391.04 | D7: =Assumptions!$B$15*Assumptions!$B$16^'Run Timeline'!D7 -> 83.037656 | E7: =Assumptions!$B$17*Assumptions!$B$18^4 -> 610.35156 | F7: 100000 | G7: 100000 | H7: 180 | I7: =D7/C7*60 -> 3.5816794 | J7: =E7/C7*60 -> 26.326413 | K7: =F7/C7*60 -> 4313.3195 | L7: =G7/C7*60 -> 4313.3195 | M7: =H7/C7*60 -> 7.7639752 | N7: =IF(SUMPRODUCT((I7:M7>=Assumptions!$B$26)*(I7:M7<=Assumptions!$B$27))>0,"OK",IF(SUMPRODUCT((I7:M7<Assumptions!$B$26))>0,"TRIVIAL-ONLY","WALL")) -> OK
A8: H5 | B8: ='Run Timeline'!G8 -> 4665.6 | C8: =B8*Assumptions!$B$14 -> 2332.8 | D8: =Assumptions!$B$15*Assumptions!$B$16^'Run Timeline'!D8 -> 112.10084 | E8: =Assumptions!$B$17*Assumptions!$B$18^5 -> 762.93945 | F8: =Assumptions!$B$23 -> 140 | G8: =Assumptions!$B$21 -> 900 | H8: 100000 | I8: =D8/C8*60 -> 2.883252 | J8: =E8/C8*60 -> 19.622928 | K8: =F8/C8*60 -> 3.600823 | L8: =G8/C8*60 -> 23.148148 | M8: =H8/C8*60 -> 2572.0165 | N8: =IF(SUMPRODUCT((I8:M8>=Assumptions!$B$26)*(I8:M8<=Assumptions!$B$27))>0,"OK",IF(SUMPRODUCT((I8:M8<Assumptions!$B$26))>0,"TRIVIAL-ONLY","WALL")) -> OK
A9: H6 | B9: ='Run Timeline'!G9 -> 5184 | C9: =B9*Assumptions!$B$14 -> 2592 | D9: =Assumptions!$B$15*Assumptions!$B$16^'Run Timeline'!D9 -> 151.33613 | E9: =Assumptions!$B$17*Assumptions!$B$18^6 -> 953.67432 | F9: 100000 | G9: 100000 | H9: 260 | I9: =D9/C9*60 -> 3.5031511 | J9: =E9/C9*60 -> 22.075794 | K9: =F9/C9*60 -> 2314.8148 | L9: =G9/C9*60 -> 2314.8148 | M9: =H9/C9*60 -> 6.0185185 | N9: =IF(SUMPRODUCT((I9:M9>=Assumptions!$B$26)*(I9:M9<=Assumptions!$B$27))>0,"OK",IF(SUMPRODUCT((I9:M9<Assumptions!$B$26))>0,"TRIVIAL-ONLY","WALL")) -> OK
A10: H7 | B10: ='Run Timeline'!G10 -> 7188.48 | C10: =B10*Assumptions!$B$14 -> 3594.24 | D10: =Assumptions!$B$15*Assumptions!$B$16^'Run Timeline'!D10 -> 151.33613 | E10: =Assumptions!$B$17*Assumptions!$B$18^7 -> 1192.0929 | F10: =Assumptions!$B$24 -> 320 | G10: 100000 | H10: 100000 | I10: =D10/C10*60 -> 2.5263109 | J10: =E10/C10*60 -> 19.900055 | K10: =F10/C10*60 -> 5.3418803 | L10: =G10/C10*60 -> 1669.3376 | M10: =H10/C10*60 -> 1669.3376 | N10: =IF(SUMPRODUCT((I10:M10>=Assumptions!$B$26)*(I10:M10<=Assumptions!$B$27))>0,"OK",IF(SUMPRODUCT((I10:M10<Assumptions!$B$26))>0,"TRIVIAL-ONLY","WALL")) -> OK
A11: H8 (fold) | B11: ='Run Timeline'!G11 -> 7637.76 | C11: =B11*Assumptions!$B$14 -> 3818.88 | D11: =Assumptions!$B$15*Assumptions!$B$16^'Run Timeline'!D11 -> 204.30377 | E11: =Assumptions!$B$17*Assumptions!$B$18^8 -> 1490.1161 | F11: 100000 | G11: 100000 | H11: 100000 | I11: =D11/C11*60 -> 3.2099009 | J11: =E11/C11*60 -> 23.411829 | K11: =F11/C11*60 -> 1571.1413 | L11: =G11/C11*60 -> 1571.1413 | M11: =H11/C11*60 -> 1571.1413 | N11: =IF(SUMPRODUCT((I11:M11>=Assumptions!$B$26)*(I11:M11<=Assumptions!$B$27))>0,"OK",IF(SUMPRODUCT((I11:M11<Assumptions!$B$26))>0,"TRIVIAL-ONLY","WALL")) -> OK
A13: Sentinel 100,000 = option not available that hour (reads as absurd minutes; ignored by the band unless nothing else exists).
A14: Verdict meanings: OK = at least one purchase lands in the band. TRIVIAL-ONLY = everything affordable is <10 min (income has outrun the sinks -> raise replant cap / add building levels). WALL = nothing under 90 min (sinks have outrun income).

Sheet Offline Check
A1: Overnight earnings — small crew, v0.11 stationing (assigned gatherers; unheld trail = x0.5 of one post; wanderers x0.5)
A3: Ground gatherers (assigned) | B3: Demand / hr | C3: Trail-post haul cap | D3: Eff / hr (1 post) | E3: @4 h cap | F3: @6 h cap | G3: @8 h cap | H3: Note
A4: 2 gatherers (+1 on the trail) | B4: =2*Assumptions!$B$5*Assumptions!$B$29*Assumptions!$B$30 -> 1248 | C4: =4*Assumptions!$B$5*Assumptions!$B$29*Assumptions!$B$30*Assumptions!$B$31 -> 1872 | D4: =MIN(B4,C4) -> 1248 | E4: =D4*4 -> 4992 | F4: =D4*6 -> 7488 | G4: =D4*8 -> 9984
A5: 3 gatherers (+1 on the trail) | B5: =3*Assumptions!$B$5*Assumptions!$B$29*Assumptions!$B$30 -> 1872 | C5: =4*Assumptions!$B$5*Assumptions!$B$29*Assumptions!$B$30*Assumptions!$B$31 -> 1872 | D5: =MIN(B5,C5) -> 1872 | E5: =D5*4 -> 7488 | F5: =D5*6 -> 11232 | G5: =D5*8 -> 14976
A6: 4 gatherers (+1 on the trail) | B6: =4*Assumptions!$B$5*Assumptions!$B$29*Assumptions!$B$30 -> 2496 | C6: =4*Assumptions!$B$5*Assumptions!$B$29*Assumptions!$B$30*Assumptions!$B$31 -> 1872 | D6: =MIN(B6,C6) -> 1872 | E6: =D6*4 -> 7488 | F6: =D6*6 -> 11232 | G6: =D6*8 -> 14976 | H6: haul-capped — assign or wing
A7: 5 gatherers (+1 on the trail) | B7: =5*Assumptions!$B$5*Assumptions!$B$29*Assumptions!$B$30 -> 3120 | C7: =4*Assumptions!$B$5*Assumptions!$B$29*Assumptions!$B$30*Assumptions!$B$31 -> 1872 | D7: =MIN(B7,C7) -> 1872 | E7: =D7*4 -> 7488 | F7: =D7*6 -> 11232 | G7: =D7*8 -> 14976 | H7: haul-capped — assign or wing
A9: With Spare Wing (2 trail posts held)
A10: 4 gatherers, 2 posts held | B10: =4*Assumptions!$B$5*Assumptions!$B$29*Assumptions!$B$30 -> 2496 | C10: =2*4*Assumptions!$B$5*Assumptions!$B$29*Assumptions!$B$30*Assumptions!$B$31 -> 3744 | D10: =MIN(B10,C10) -> 2496 | F10: =D10*6 -> 14976 | H10: the 2nd post relieves the cap — the SP-1 stance
A11: 5 gatherers, 2 posts held | B11: =5*Assumptions!$B$5*Assumptions!$B$29*Assumptions!$B$30 -> 3120 | C11: =2*4*Assumptions!$B$5*Assumptions!$B$29*Assumptions!$B$30*Assumptions!$B$31 -> 3744 | D11: =MIN(B11,C11) -> 3120 | F11: =D11*6 -> 18720 | H11: the 2nd post relieves the cap — the SP-1 stance
A13: Benchmark: overnight @6 h vs. Day-2 shopping list (Zone 4 provisions + bronze batch + building L5)
A14: Shopping list value | B14: =Assumptions!$B$21+Assumptions!$B$23+Assumptions!$B$17*Assumptions!$B$18^5 -> 1802.9395
A15: 3-agent overnight @6 h covers | B15: =F5/B14 -> 6.2298265 | C15: Target: >=1.0x — a night away should fund the morning's plans, not dwarf a week of play.

Sheet Findings
A1: Findings — ECO-1 seed model
A3: 1 | B3: Hour-six proof PASSES on defaults: every hour block verdicts OK on the SinkLadder. But the band-holder is the BUILDING line (~20-30 min per level all run), not replanting: a single replant level goes trivial (<10 min) from H2 onward at r=1.35. Recommendation: either raise r toward 1.5-1.6 so late richness levels re-enter the band, or sell replants in multi-level batches - and protect the building lines, because if they starve the whole ladder drifts TRIVIAL-ONLY.
A4: 2 | B4: Solved constants (Run Timeline, yellow): K (Verdure) ~ 425 and K_f (Kinship) ~ 650 at defaults - DERIVED as Renown-at-fold / target^2, not guessed. They recompute automatically when any input moves; adopt the solved values into design/data as starting constants.
A5: 3 | B5: The Rite's Renown share is ~10% of lifetime Renown at defaults (4,000 of ~42,500) - offerings genuinely never tax prestige, but they are not yet a MAJOR contributor either. If the fold forecast should visibly jump on verse completion (the chunky-Renown intent), raise authored offering quantities or the deed/specimen fixed grants.
A6: 4 | B6: Offline is generous within genre norms: 3 assigned gatherers overnight at the 6 h cap earn ~11,200 goods = about 2.4 active hours, covering the Day-2 shopping list ~6x. At 4+ gatherers a single held trail post binds (demand 2,496/hr vs post cap 1,872/hr) - visible haul-capping that makes Spare Wing legible. SP-1 stance encoded: one post = 75% of a 4-gatherer demand; hauling equipment tuned against 2 eventual posts. v0.11 wandering means an unheld trail still moves x0.5 of one post - the model's MIN() shape is unchanged, only the floor rose.
A7: 5 | B7: TRIVIAL-ONLY is the failure mode to watch, not WALL: income compounds (tools x richness x agents) faster than any single sink curve. The two levers are the replant ratio/cap and the bottomless building lines; the four-way goods dilemma (kit/caravan/spirits/land) is what holds late-run tension.
A8: 6 | B8: Everything here is placeholder-by-design: blue cells are the levers. The Phase 3 balance pass should extend this to per-resource detail, the wanderer x0.5 floor, and runs 2-5 for the Rite generator proof.
